tflibrary/__init__.py
tflibrary/config_manager.py
tflibrary/logger.py
tflibrary/tf_oss.py
thefiarlib-0.0.8b0.dist-info/DESCRIPTION.rst
thefiarlib-0.0.8b0.dist-info/METADATA
thefiarlib-0.0.8b0.dist-info/RECORD
thefiarlib-0.0.8b0.dist-info/WHEEL
thefiarlib-0.0.8b0.dist-info/metadata.json
thefiarlib-0.0.8b0.dist-info/top_level.txt
