Metadata-Version: 2.0
Name: thefiarlib
Version: 0.0.8b0
Summary: thefiarlib
Home-page: UNKNOWN
Author: tf
Author-email: tf@thefair.net.cn
License: MIT
Platform: UNKNOWN
Classifier: Development Status :: 4 - Beta
Classifier: Intended Audience :: Developers
Classifier: Topic :: Software Development :: Build Tools
Classifier: License :: OSI Approved :: MIT License
Classifier: Programming Language :: Python :: 3.6
Requires-Dist: PyDispatcher
Requires-Dist: PyMySQL (==0.9.2)
Requires-Dist: Scrapy (==1.5.1)
Requires-Dist: aliyun-python-sdk-core-v3 (==2.8.9)
Requires-Dist: aliyun-python-sdk-green (==3.4.1)
Requires-Dist: aliyunsdkcore
Requires-Dist: asstosrt
Requires-Dist: beautifulsoup4 (==4.7.1)
Requires-Dist: chardet
Requires-Dist: click
Requires-Dist: elasticsearch (==5.5.3)
Requires-Dist: elasticsearch-dsl (==5.4.0)
Requires-Dist: flask (==1.0.2)
Requires-Dist: librosa (==0.6.3)
Requires-Dist: matplotlib (==3.0.3)
Requires-Dist: oss2 (==2.5.0)
Requires-Dist: pandas (==0.24.2)
Requires-Dist: pika
Requires-Dist: pymongo (==3.7.1)
Requires-Dist: python-Levenshtein (==0.12.0)
Requires-Dist: python-crontab
Requires-Dist: python-unsplash (==1.0.1)
Requires-Dist: pytz (==2018.5)
Requires-Dist: qiniu (==7.2.2)
Requires-Dist: redis (==2.10.6)
Requires-Dist: requests (==2.13.0)
Requires-Dist: scrapy-djangoitem (==1.1.1)
Requires-Dist: six (==1.10.0)
Requires-Dist: thrift (==0.11.0)
Requires-Dist: urllib3 (==1.21.1)
Requires-Dist: webrtcvad (==2.0.10)
Requires-Dist: websocket
Requires-Dist: xlsxwriter
